pywebnn-0.5.11.dist-info/METADATA
pywebnn-0.5.11.dist-info/WHEEL
pywebnn-0.5.11.dist-info/licenses/LICENSE
webnn/__init__.py
webnn/__init__.pyi
webnn/_rustnn.cpython-312-x86_64-linux-gnu.so
webnn/hub.py
pywebnn-0.5.11.dist-info/RECORD
