Metadata-Version: 2.4
Name: pywebnn
Version: 0.5.11
Classifier: Development Status :: 3 - Alpha
Classifier: Intended Audience :: Developers
Classifier: Intended Audience :: Science/Research
Classifier: License :: OSI Approved :: Apache Software License
Classifier: Operating System :: OS Independent
Classifier: Programming Language :: Python :: 3
Classifier: Programming Language :: Python :: 3.12
Classifier: Programming Language :: Python :: 3.13
Classifier: Programming Language :: Python :: Implementation :: CPython
Classifier: Programming Language :: Rust
Classifier: Topic :: Scientific/Engineering :: Artificial Intelligence
Classifier: Topic :: Software Development :: Libraries :: Python Modules
Requires-Dist: numpy>=1.20.0
Requires-Dist: onnxruntime>=1.23.0
Requires-Dist: pytest>=7.0 ; extra == 'dev'
Requires-Dist: pytest-asyncio>=0.21.0 ; extra == 'dev'
Requires-Dist: maturin>=1.0 ; extra == 'dev'
Provides-Extra: dev
License-File: LICENSE
Summary: EXPERIMENTAL: Python bindings for W3C WebNN API - Neural network graph validation, ONNX/CoreML conversion, and cross-platform execution with CPU/GPU/NPU support
Keywords: webnn,neural-network,machine-learning,onnx,coreml,ai,graph,inference
Author-email: Tarek Ziade <tarek@ziade.org>
License: Apache-2.0
Requires-Python: >=3.11
Project-URL: Homepage, https://github.com/tarekziade/rustnn
Project-URL: Documentation, https://tarekziade.github.io/rustnn/
Project-URL: Repository, https://github.com/tarekziade/rustnn
Project-URL: Issues, https://github.com/tarekziade/rustnn/issues
Project-URL: Changelog, https://github.com/tarekziade/rustnn/releases
